{"invariant": {"first_name": "Jane", "color_info": {"favorite_color": "blue", "rgb_value": "FF0000"}, "total_weight_gain": 2.5, "gender": "female"}, "2010": {"weight_in_pounds": 120.6}, "2011": {"weight_in_pounds": 126.2}, "2012": {"weight_in_pounds": 119.0}, "2013": {"weight_in_pounds": 123.1}, "J": {"a": {"n": {"e": {"'": {"s": {" ": {"f": {"a": {"v": {"o": {"r": {"i": {"t": {"e": {" ": {"c": {"o": {"l": {"o": {"r": {" ": {"i": {"s": {" ": {"b": {"l": {"u": {"e": {" ": {"(": {"F": {"F": {"0": {"0": {"0": {"0": {")": {".": {" ": {"O": {"v": {"e": {"r": {" ": {"t": {"h": {"e": {" ": {"o": {"b": {"s": {"e": {"r": {"v": {"a": {"t": {"i": {"o": {"n": {" ": {"p": {"e": {"r": {"i": {"o": {"d": {",": {" ": {"s": {"h": {"e": {" ": {"g": {"a": {"i": {"n": {"e": {"d": {" ": {"2": {".": {"5": {" ": {"l": {"b": {"s": {".": ["invariant", "personal_summary"]}}}}}}}}}}}}}}}}}}}}}}}}}}}}}}}}}}}}}}}}}}}}}}}}}}}}}}}}}}}}}}}}}}}}}}}}}}}}}}}}}}}}}}}}