{
    "1": {
        "source_string": "GHI",
        "source_binary": true,
        "source_unary": true
    },
    "immutable": {
        "some_folder":  {
            "random_field": "Y"
        },
        "outer_list_1": [
            {
                "inner_list": [
                    {"name": "D_1_1_1"},
                    {"name": "D_1_1_2"}
                ]
            }
        ],
        "outer_list_2": [
            {
                "inner_list": [
                    {"name": "C_2_1_1"},
                    {"name": "C_2_1_2"}
                ]
            }
        ]
    }
}
